.mina/core.toml
arclet/alconna/graia/__init__.py
arclet/alconna/graia/adapter.py
arclet/alconna/graia/alc.py
arclet/alconna/graia/argv.py
arclet/alconna/graia/create.py
arclet/alconna/graia/dispatcher.py
arclet/alconna/graia/i18n/.config.json
arclet/alconna/graia/i18n/.lang.schema.json
arclet/alconna/graia/i18n/.template.json
arclet/alconna/graia/i18n/.template.schema.json
arclet/alconna/graia/i18n/__init__.py
arclet/alconna/graia/i18n/en-US.json
arclet/alconna/graia/i18n/zh-CN.json
arclet/alconna/graia/model.py
arclet/alconna/graia/saya.py
arclet/alconna/graia/service.py
arclet/alconna/graia/tools.py
arclet/alconna/graia/utils.py
arclet_alconna_graia-0.18.3.dist-info/METADATA
arclet_alconna_graia-0.18.3.dist-info/WHEEL
arclet_alconna_graia-0.18.3.dist-info/entry_points.txt
arclet_alconna_graia-0.18.3.dist-info/licenses/LICENSE
arclet_alconna_graia-0.18.3.dist-info/RECORD
