Metadata-Version: 2.1
Name: arclet-alconna-graia
Version: 0.18.3
Summary: Support Alconna to GraiaProject
Keywords: alconna,graia,arclet,ariadne
Home-page: https://github.com/ArcletProject/Alconna-Graia
Author-Email: RF-Tar-Railt <rf_tar_railt@qq.com>
License: AGPL-3.0
Classifier: Development Status :: 4 - Beta
Classifier: License :: OSI Approved :: GNU Affero General Public License v3
Classifier: Operating System :: OS Independent
Classifier: Programming Language :: Python :: 3.10
Classifier: Programming Language :: Python :: 3.8
Classifier: Programming Language :: Python :: 3.9
Project-URL: Homepage, https://github.com/ArcletProject/Alconna-Graia
Project-URL: Repository, https://github.com/ArcletProject/Alconna-Graia
Project-URL: Documentation, https://arcletproject.github.io/docs/alconna/tutorial
Project-URL: Bug reports, https://github.com/ArcletProject/Alconna/issues
Project-URL: Source, https://github.com/ArcletProject/Alconna
Requires-Python: >=3.8
Requires-Dist: arclet-alconna<2.0.0,>=1.8.12
Requires-Dist: arclet-alconna-tools<0.8.0,>=0.7.4
Requires-Dist: tarina>=0.5.0
Requires-Dist: nepattern<0.8.0,>=0.7.3
Requires-Dist: creart>=0.3.0
Requires-Dist: graia-amnesia>=0.5.0
Requires-Dist: graia-broadcast>=0.18.2
Requires-Dist: graia-saya>=0.0.17
Requires-Dist: launart>=0.5.0
